b2w
