Metadata-Version: 1.0
Name: python-bonmarketplace-b2w
Version: 1.0.1b
Summary: Cliente Python para integração com Bon Marketplace B2W (Shoptime, Lojas Americanas, Submarino e Soubarato)
Home-page: https://github.com/gabrielgaliaso/python-bonmarketplace-b2w
Author: Gabriel Galiaso
Author-email: gabriel@poteinterativo.com.br
License: MIT
Keywords: b2w,submarino,americanas,shoptime,soubarato,lojas,marketplace,ecommerce,e-commerce,virtual
Platform: UNKNOWN
Classifier: Programming Language :: Python
Classifier: Topic :: Software Development :: Libraries :: Python Modules
